data_science_pro/__init__.py
data_science_pro/pipeline.py
data_science_pro/api/__init__.py
data_science_pro/api/llm_connector.py
data_science_pro/cycle/__init__.py
data_science_pro/cycle/controller.py
data_science_pro/cycle/critic.py
data_science_pro/cycle/indexer.py
data_science_pro/cycle/orchestrator.py
data_science_pro/cycle/planner.py
data_science_pro/cycle/reporter.py
data_science_pro/cycle/retriever.py
data_science_pro/cycle/suggester.py
data_science_pro/cycle/target_selector.py
data_science_pro/data/__init__.py
data_science_pro/data/data_analyzer.py
data_science_pro/data/data_loader.py
data_science_pro/data/data_operations.py
data_science_pro/modeling/__init__.py
data_science_pro/modeling/evaluator.py
data_science_pro/modeling/registry.py
data_science_pro/modeling/trainer.py
data_science_pro/utils/__init__.py
data_science_pro/utils/prompts.py
data_science_pro/utils/rag.py
data_science_pro-0.2.0.dist-info/METADATA
data_science_pro-0.2.0.dist-info/WHEEL
data_science_pro-0.2.0.dist-info/entry_points.txt
data_science_pro-0.2.0.dist-info/top_level.txt
data_science_pro-0.2.0.dist-info/RECORD
