Metadata-Version: 2.1
Name: data_science_pro
Version: 0.2.0
Summary: LLM-powered modular data science pipeline
Author: Rajratan More
Requires-Python: >=3.8
Requires-Dist: pandas
Requires-Dist: numpy
Requires-Dist: scikit-learn
Requires-Dist: imbalanced-learn
Requires-Dist: joblib
Requires-Dist: langchain
Requires-Dist: langchain-community
Requires-Dist: langchain-openai
Requires-Dist: langgraph
Requires-Dist: chromadb
Requires-Dist: openai
Requires-Dist: python-dotenv
